piniverse/__init__.py
piniverse/api.py
piniverse/common/__init__.py
piniverse/common/exceptions/__init__.py
piniverse/common/exceptions/pin_exception.py
piniverse/common/monostate/__init__.py
piniverse/common/monostate/borg.py
piniverse/common/responsibilities/__init__.py
piniverse/common/responsibilities/responsibility.py
piniverse/common/visitors/__init__.py
piniverse/common/visitors/visitor.py
piniverse/contributions/__init__.py
piniverse/core/__init__.py
piniverse/core/module_finder.py
piniverse/core/pin.py
piniverse/core/pin_drawer.py
piniverse/core/pin_finder.py
piniverse/core/pin_node.py
piniverse/core/pin_store.py
piniverse/core/tags.py
piniverse/ui/__init__.py
piniverse/ui/drawer.py
piniverse-0.0.3.dist-info/LICENSE
piniverse-0.0.3.dist-info/METADATA
piniverse-0.0.3.dist-info/WHEEL
piniverse-0.0.3.dist-info/top_level.txt
piniverse-0.0.3.dist-info/RECORD
